README.md
setup.py
cleandev_requests_facade.egg-info/PKG-INFO
cleandev_requests_facade.egg-info/SOURCES.txt
cleandev_requests_facade.egg-info/dependency_links.txt
cleandev_requests_facade.egg-info/requires.txt
cleandev_requests_facade.egg-info/top_level.txt
requests_facade/__init__.py
requests_facade/config.py