Metadata-Version: 2.1
Name: cleandev-requests-facade
Version: 0.1.5
Summary: Fachada para autenticación de JWT
Home-page: https://gitlab.com/cleansoftware/libs/public/cleandev-req-facade
Author: Daniel Rodriguez Rodriguez
Author-email: danielrodriguezrodriguez.pks@gmail.com
License: UNKNOWN
Project-URL: Bug Tracker, https://gitlab.com/cleansoftware/libs/public/cleandev-req-facade/-/issues
Platform: UNKNOWN
Classifier: Programming Language :: Python :: 3
Classifier: License :: OSI Approved :: MIT License
Classifier: Operating System :: OS Independent
Requires-Python: >=3.9
